flask_hashids.py
Flask_Hashids-1.0.3.dist-info/LICENSE
Flask_Hashids-1.0.3.dist-info/METADATA
Flask_Hashids-1.0.3.dist-info/WHEEL
Flask_Hashids-1.0.3.dist-info/top_level.txt
Flask_Hashids-1.0.3.dist-info/RECORD
