Metadata-Version: 2.1
Name: Flask-Hashids
Version: 1.0.3
Summary: Hashids integration for Flask applications.
Home-page: https://github.com/Pevtrick/Flask-Hashids
Author: Patrick Jentsch
Author-email: patrickjentsch@gmx.net
Classifier: Programming Language :: Python :: 3
Classifier: Framework :: Flask
Classifier: License :: OSI Approved :: MIT License
Classifier: Operating System :: OS Independent
Requires-Python: >=3.5
License-File: LICENSE
Requires-Dist: Flask>=0.7
Requires-Dist: Hashids>=1.0.2
